examapp/__init__.py
examapp/app/__init__.py
examapp/app/main.py
examapp/app/assets/__init__.py
examapp/app/assets/qA.b64
examapp/app/assets/qB.b64
examapp/app/assets/qC.b64
examapp/app/assets/qD.b64
examapp/app/assets/qE.b64
examapp/app/assets/template.ipynb
examapp/app/assets/template.json
examapp/app/lang/__init__.py
examapp/app/worker/__init__.py
examapp/app/worker/date.py
examapp/app/worker/image.py
examapp/app/worker/notebook.py
examapp/app/worker/writer.py
examapp-0.0.5.dist-info/METADATA
examapp-0.0.5.dist-info/RECORD
examapp-0.0.5.dist-info/WHEEL
examapp-0.0.5.dist-info/top_level.txt
